main.py
run.py
run_server.py
test_module.py
weknora_mcp_server.py
weknora_mcp_server-1.0.0.data/data/LICENSE
weknora_mcp_server-1.0.0.data/data/README.md
weknora_mcp_server-1.0.0.data/data/requirements.txt
weknora_mcp_server-1.0.0.dist-info/licenses/LICENSE
weknora_mcp_server-1.0.0.dist-info/METADATA
weknora_mcp_server-1.0.0.dist-info/WHEEL
weknora_mcp_server-1.0.0.dist-info/entry_points.txt
weknora_mcp_server-1.0.0.dist-info/top_level.txt
weknora_mcp_server-1.0.0.dist-info/RECORD
