Metadata-Version: 2.4
Name: weknora-mcp-server
Version: 1.0.0
Summary: WeKnora MCP Server - Model Context Protocol server for WeKnora API
Home-page: https://github.com/NannaOlympicBroadcast/WeKnoraMCP
Author: WeKnora Team
Author-email: WeKnora Team <support@weknora.com>
Maintainer-email: WeKnora Team <support@weknora.com>
License: MIT
Project-URL: Homepage, https://github.com/NannaOlympicBroadcast/WeKnoraMCP
Project-URL: Documentation, https://docs.weknora.com
Project-URL: Repository, https://github.com/NannaOlympicBroadcast/WeKnoraMCP
Project-URL: Bug Reports, https://github.com/NannaOlympicBroadcast/WeKnoraMCP/issues
Project-URL: Changelog, https://github.com/NannaOlympicBroadcast/WeKnoraMCP/blob/main/CHANGELOG.md
Keywords: mcp,model-context-protocol,weknora,knowledge-management,api-server
Classifier: Development Status :: 4 - Beta
Classifier: Intended Audience :: Developers
Classifier: License :: OSI Approved :: MIT License
Classifier: Operating System :: OS Independent
Classifier: Programming Language :: Python :: 3
Classifier: Programming Language :: Python :: 3.8
Classifier: Programming Language :: Python :: 3.9
Classifier: Programming Language :: Python :: 3.10
Classifier: Programming Language :: Python :: 3.11
Classifier: Programming Language :: Python :: 3.12
Classifier: Topic :: Software Development :: Libraries :: Python Modules
Classifier: Topic :: Internet :: WWW/HTTP :: HTTP Servers
Classifier: Topic :: Scientific/Engineering :: Artificial Intelligence
Requires-Python: >=3.8
License-File: LICENSE
Requires-Dist: mcp>=1.0.0
Requires-Dist: requests>=2.31.0
Provides-Extra: dev
Requires-Dist: pytest>=7.0; extra == "dev"
Requires-Dist: pytest-asyncio>=0.21.0; extra == "dev"
Requires-Dist: black>=23.0; extra == "dev"
Requires-Dist: flake8>=6.0; extra == "dev"
Requires-Dist: mypy>=1.0; extra == "dev"
Provides-Extra: test
Requires-Dist: pytest>=7.0; extra == "test"
Requires-Dist: pytest-asyncio>=0.21.0; extra == "test"
Requires-Dist: pytest-cov>=4.0; extra == "test"
Dynamic: author
Dynamic: home-page
Dynamic: license-file
Dynamic: requires-python
